.DS_Store
enerpi/__init__.py
enerpi/__main__.py
enerpi/api.py
enerpi/base.py
enerpi/calibrate.py
enerpi/catalog.py
enerpi/command_enerpi.py
enerpi/daemon.py
enerpi/database.py
enerpi/editconf.py
enerpi/enerdaemon.py
enerpi/enerpimeter.py
enerpi/iobroadcast.py
enerpi/ledrgb.py
enerpi/pisampler.py
enerpi/config/.enerpi_data_path
enerpi/config/__init__.py
enerpi/config/crontasks.py
enerpi/config/default_config_enerpi.ini
enerpi/config/default_sensors_enerpi.json
enerpi/cronip/__init__.py
enerpi/gdrivesync/__init__.py
enerpi/hdftscat/__init__.py
enerpi/notifier/__init__.py
enerpi/pitemps/__init__.py
enerpi/pitemps/__main__.py
enerpi/prettyprinting/__init__.py
enerpi-0.9.7.dist-info/DESCRIPTION.rst
enerpi-0.9.7.dist-info/LICENSE.txt
enerpi-0.9.7.dist-info/METADATA
enerpi-0.9.7.dist-info/RECORD
enerpi-0.9.7.dist-info/WHEEL
enerpi-0.9.7.dist-info/entry_points.txt
enerpi-0.9.7.dist-info/metadata.json
enerpi-0.9.7.dist-info/top_level.txt
enerpiplot/__init__.py
enerpiplot/enerplot.py
enerpiplot/mule_rscgen.py
enerpiplot/plotbokeh.py
enerpiweb/__init__.py
enerpiweb/__main__.py
enerpiweb/command_enerpiweb.py
enerpiweb/emailing.py
enerpiweb/facturacionpvpc.py
enerpiweb/forms.py
enerpiweb/rt_stream.py
enerpiweb/utils.py
enerpiweb/views.py
enerpiweb/views_filehandler.py
enerpiweb/static/css/bootstrap-select.css
enerpiweb/static/css/bootstrap-select.min.css
enerpiweb/static/css/bootstrap-switch.css
enerpiweb/static/css/bootstrap-switch.min.css
enerpiweb/static/css/navbar_custom.css
enerpiweb/static/css/tiles.css
enerpiweb/static/img/icons/Icon-Small-40@2x.png
enerpiweb/static/img/icons/android-chrome-192x192.png
enerpiweb/static/img/icons/android-chrome-512x512.png
enerpiweb/static/img/icons/apple-touch-icon-precomposed.png
enerpiweb/static/img/icons/apple-touch-icon.png
enerpiweb/static/img/icons/base.svg
enerpiweb/static/img/icons/browserconfig.xml
enerpiweb/static/img/icons/favicon-16x16.png
enerpiweb/static/img/icons/favicon-32x32.png
enerpiweb/static/img/icons/favicon.ico
enerpiweb/static/img/icons/itunesartwork.png
enerpiweb/static/img/icons/itunesartwork.svg
enerpiweb/static/img/icons/manifest.json
enerpiweb/static/img/icons/mstile-144x144.png
