Metadata-Version: 2.0
Name: enerpi
Version: 0.9.7
Summary: AC Current Meter for Raspberry PI with GPIOZERO and MCP3008
Home-page: https://github.com/azogue/enerpi
Author: Eugenio Panadero
Author-email: azogue.lab@gmail.com
License: MIT
Keywords: enerpi current gpiozero raspberry analog
Platform: UNKNOWN
Classifier: Development Status :: 3 - Alpha
Classifier: Environment :: Console
Classifier: Intended Audience :: Developers
Classifier: Intended Audience :: Education
Classifier: Intended Audience :: Information Technology
Classifier: Intended Audience :: Science/Research
Classifier: Topic :: Home Automation
Classifier: Topic :: Scientific/Engineering :: Information Analysis
Classifier: Natural Language :: Spanish
Classifier: License :: OSI Approved :: MIT License
Classifier: Programming Language :: Python :: 3.5
Classifier: Operating System :: Unix
Requires-Dist: Flask-Mail (>=0.9.1)
Requires-Dist: Flask-WTF (>=0.13.1)
Requires-Dist: RPi.GPIO (>=0.6.3)
Requires-Dist: bokeh (>=0.12.3)
Requires-Dist: croniter (>=0.3.16)
Requires-Dist: cryptography (>=1.5.2)
Requires-Dist: esiosdata (>=0.6.10)
Requires-Dist: flask (>=0.11.1)
Requires-Dist: flask-autodoc (>=0.1.2)
Requires-Dist: gpiozero (>=1.3.1)
Requires-Dist: jsondiff (>=1.0.0)
Requires-Dist: matplotlib (>=1.5.3)
Requires-Dist: numpy (>=1.11.2)
Requires-Dist: pandas (>=0.19.0)
Requires-Dist: pillow (>=4.0.0)
Requires-Dist: pushbullet.py (>=0.10.0)
Requires-Dist: python-crontab (>=2.1.1)
Requires-Dist: python-dateutil (>=2.6.0)
Requires-Dist: pytz (>=2016.7)
Requires-Dist: termcolor (>=1.1.0)
Requires-Dist: uwsgi (>=2.0.15)
Requires-Dist: werkzeug (>=0.11.11)
Requires-Dist: wtforms (>=2.1)
